brew_view/__init__.py
brew_view/__main__.py
brew_view/_version.py
brew_view/authorization.py
brew_view/base_handler.py
brew_view/metrics.py
brew_view/publishers.py
brew_view/scheduler.py
brew_view/specification.py
brew_view/controllers/__init__.py
brew_view/controllers/admin_api.py
brew_view/controllers/command_api.py
brew_view/controllers/command_list_api.py
brew_view/controllers/event_api.py
brew_view/controllers/instance_api.py
brew_view/controllers/job_api.py
brew_view/controllers/job_list_api.py
brew_view/controllers/logging_api.py
brew_view/controllers/misc_controllers.py
brew_view/controllers/permissions_api.py
brew_view/controllers/queue_api.py
brew_view/controllers/queue_list_api.py
brew_view/controllers/request_api.py
brew_view/controllers/request_list_api.py
brew_view/controllers/roles_api.py
brew_view/controllers/system_api.py
brew_view/controllers/system_list_api.py
brew_view/controllers/token_api.py
brew_view/controllers/users_api.py
brew_view/static/dist/dark.css
brew_view/static/dist/dark.js
brew_view/static/dist/dark.js.map
brew_view/static/dist/index.css
brew_view/static/dist/index.html
brew_view/static/dist/index.js
brew_view/static/dist/index.js.map
brew_view/static/dist/vendor.css
brew_view/static/dist/vendor.js
brew_view/static/dist/vendor.js.map
brew_view/static/dist/worker-json.js
brew_view/static/dist/image/fa-beer.png
brew_view/static/dist/image/fa-coffee.png
brew_view/static/dist/swagger/README.md
brew_view/static/dist/swagger/absolute-path.js
brew_view/static/dist/swagger/favicon-16x16.png
brew_view/static/dist/swagger/favicon-32x32.png
brew_view/static/dist/swagger/index.html
brew_view/static/dist/swagger/index.js
brew_view/static/dist/swagger/oauth2-redirect.html
brew_view/static/dist/swagger/package.json
brew_view/static/dist/swagger/swagger-ui-bundle.js
brew_view/static/dist/swagger/swagger-ui-bundle.js.map
brew_view/static/dist/swagger/swagger-ui-es-bundle-core.js
brew_view/static/dist/swagger/swagger-ui-es-bundle-core.js.map
brew_view-2.4.21.dist-info/LICENSE.md
brew_view-2.4.21.dist-info/METADATA
brew_view-2.4.21.dist-info/WHEEL
brew_view-2.4.21.dist-info/entry_points.txt
brew_view-2.4.21.dist-info/top_level.txt
brew_view-2.4.21.dist-info/RECORD
