Metadata-Version: 2.1
Name: brew-view
Version: 2.4.21
Summary: Beergarden Frontend
Home-page: https://beer-garden.io/
Author: The beer-garden Team
Author-email: 
License: MIT
Platform: UNKNOWN
Requires-Dist: apispec (==0.38.0)
Requires-Dist: apscheduler (==3.5.1)
Requires-Dist: bg-utils (>=2.4.10)
Requires-Dist: prometheus-client (==0.3.1)
Requires-Dist: pymongo (<4)
Requires-Dist: pyyaml (<6)
Requires-Dist: tornado (==5.1)
Requires-Dist: futures (>=3.1.1) ; python_version=="2.7"
